pysatochip/CardConnector.py
pysatochip/CardDataParser.py
pysatochip/JCconstants.py
pysatochip/Satochip2FA.py
pysatochip/SecretDecryption.py
pysatochip/SecureChannel.py
pysatochip/TxParser.py
pysatochip/__init__.py
pysatochip/certificate_validator.py
pysatochip/ecc.py
pysatochip/electrum_mnemonic.py
pysatochip/satochip_cli.py
pysatochip/slip44.py
pysatochip/util.py
pysatochip/version.py
pysatochip/cert/ca.cert
pysatochip/cert/subca-satochip.cert
pysatochip/cert/subca-satodime.cert
pysatochip/cert/subca-seedkeeper.cert
pysatochip/cert/test-ca.cert
pysatochip/cert/test-subca-satochip.cert
pysatochip/cert/test-subca-satodime.cert
pysatochip/cert/test-subca-seedkeeper.cert
pysatochip-0.17.0.dist-info/LICENSE
pysatochip-0.17.0.dist-info/METADATA
pysatochip-0.17.0.dist-info/WHEEL
pysatochip-0.17.0.dist-info/entry_points.txt
pysatochip-0.17.0.dist-info/top_level.txt
pysatochip-0.17.0.dist-info/RECORD
