Metadata-Version: 2.2
Name: pysatochip
Version: 0.17.0
Summary: Simple python library to communicate with a Satochip hardware wallet
Home-page: https://github.com/Toporin/pysatochip
Author: Toporin
Author-email: satochip.wallet@gmail.com
Project-URL: Github, https://github.com/Toporin
Project-URL: Webshop, https://satochip.io/
Project-URL: Telegram, https://t.me/Satochip
Project-URL: Twitter, https://twitter.com/satochip
Project-URL: Source, https://github.com/Toporin/pysatochip/
Project-URL: Tracker, https://github.com/Toporin/pysatochip/issues
Classifier: Programming Language :: Python :: 3
Classifier: License :: OSI Approved :: GNU Lesser General Public License v3 (LGPLv3)
Classifier: Operating System :: OS Independent
Requires-Python: >=3.6
License-File: LICENSE
Requires-Dist: pyscard>=1.9.9
Requires-Dist: ecdsa>=0.15
Requires-Dist: pyaes>=1.6.1
Requires-Dist: cryptography>=3.3.2
Requires-Dist: pyopenssl>=20.0.0
Requires-Dist: certifi
Provides-Extra: cli
Requires-Dist: mnemonic; extra == "cli"
Requires-Dist: click; extra == "cli"
Requires-Dist: websockets; extra == "cli"
Requires-Dist: nostr; extra == "cli"
Requires-Dist: cbor2; extra == "cli"
Dynamic: author
Dynamic: author-email
Dynamic: classifier
Dynamic: description
Dynamic: description-content-type
Dynamic: home-page
Dynamic: project-url
Dynamic: provides-extra
Dynamic: requires-dist
Dynamic: requires-python
Dynamic: summary
